lilya/__init__.py
lilya/__main__.py
lilya/_utils.py
lilya/apps.py
lilya/authentication.py
lilya/background.py
lilya/clientip.py
lilya/compat.py
lilya/concurrency.py
lilya/context.py
lilya/controllers.py
lilya/datastructures.py
lilya/decorators.py
lilya/dependencies.py
lilya/encoders.py
lilya/enums.py
lilya/environments.py
lilya/exceptions.py
lilya/lifecycle.py
lilya/logging.py
lilya/params.py
lilya/py.typed
lilya/ranges.py
lilya/requests.py
lilya/responses.py
lilya/routing.py
lilya/serializers.py
lilya/staticfiles.py
lilya/status.py
lilya/transformers.py
lilya/types.py
lilya/websockets.py
lilya/_internal/__init__.py
lilya/_internal/_connection.py
lilya/_internal/_crypto.py
lilya/_internal/_encoders.py
lilya/_internal/_encoding.py
lilya/_internal/_events.py
lilya/_internal/_exception_handlers.py
lilya/_internal/_helpers.py
lilya/_internal/_inspect.py
lilya/_internal/_message.py
lilya/_internal/_middleware.py
lilya/_internal/_module_loading.py
lilya/_internal/_parsers.py
lilya/_internal/_path.py
lilya/_internal/_path_transformers.py
lilya/_internal/_permissions.py
lilya/_internal/_representation.py
lilya/_internal/_responses.py
lilya/_internal/_scopes.py
lilya/_internal/_urls.py
lilya/_internal/_templates/__init__.py
lilya/_internal/_templates/app_template/__init__.py-tpl
lilya/_internal/_templates/app_template/tests.py-tpl
lilya/_internal/_templates/app_template/directives/__init__.py-tpl
lilya/_internal/_templates/app_template/directives/operations/__init__.py-tpl
lilya/_internal/_templates/app_template/{{ api_version }}/__init__.py-tpl
lilya/_internal/_templates/app_template/{{ api_version }}/controllers.py-tpl
lilya/_internal/_templates/app_template/{{ api_version }}/schemas.py-tpl
lilya/_internal/_templates/app_template/{{ api_version }}/urls.py-tpl
lilya/_internal/_templates/deployment_template/docker/Dockerfile.e-tpl
lilya/_internal/_templates/deployment_template/gunicorn/gunicorn_conf.py.e-tpl
lilya-0.23.2.dist-info/METADATA
lilya-0.23.2.dist-info/WHEEL
lilya-0.23.2.dist-info/entry_points.txt
lilya-0.23.2.dist-info/licenses/LICENSE
lilya-0.23.2.dist-info/RECORD
