Metadata-Version: 2.4
Name: lilya
Version: 0.23.2
Summary: Yet another ASGI toolkit that delivers
Project-URL: Homepage, https://github.com/dymmond/lilya
Project-URL: Documentation, https://lilya.dev
Project-URL: Changelog, https://lilya.dev/release-notes/
Project-URL: Funding, https://github.com/sponsors/tarsil
Project-URL: Source, https://github.com/dymmond/lilya
Author-email: Tiago Silva <tiago.arasilva@gmail.com>
License-File: LICENSE
Keywords: ai,aiohttp,anyio,aop,api,api-key,api-server,asgi,async,async-framework,asyncio,authentication,auto-documentation,autodoc,backend,background-tasks,caching,cloud-native,concurrency,controllers,cors,csrf,data-validation,dependency-injection,developer-friendly,django,dymmond,esmerald,event-driven,exception-handling,fastapi,flask,graphql,graphql-support,high-performance,http,hypercorn,interceptors,json,jwt,lilya,machine-learning,microservices,middlewares,ml,modern-python,non-blocking,oauth2
Classifier: Development Status :: 4 - Beta
Classifier: Environment :: Web Environment
Classifier: Framework :: AnyIO
Classifier: Framework :: AsyncIO
Classifier: Intended Audience :: Developers
Classifier: Intended Audience :: Information Technology
Classifier: Intended Audience :: System Administrators
Classifier: License :: OSI Approved :: BSD License
Classifier: Operating System :: OS Independent
Classifier: Programming Language :: Python
Classifier: Programming Language :: Python :: 3
Classifier: Programming Language :: Python :: 3 :: Only
Classifier: Programming Language :: Python :: 3.10
Classifier: Programming Language :: Python :: 3.11
Classifier: Programming Language :: Python :: 3.12
Classifier: Programming Language :: Python :: 3.13
Classifier: Programming Language :: Python :: 3.14
Classifier: Topic :: Internet
Classifier: Topic :: Internet :: WWW/HTTP
Classifier: Topic :: Internet :: WWW/HTTP :: HTTP Servers
Classifier: Topic :: Software Development
Classifier: Topic :: Software Development :: Libraries
Classifier: Topic :: Software Development :: Libraries :: Application Frameworks
Classifier: Topic :: Software Development :: Libraries :: Python Modules
Classifier: Typing :: Typed
Requires-Python: >=3.10
Requires-Dist: anyio<5,>=3.4.0
Requires-Dist: monkay>=0.4.0
Requires-Dist: multidict<7.0.0,>=6.0.4
Requires-Dist: typing-extensions>=3.10.0; python_version < '3.11'
Provides-Extra: all
Requires-Dist: httpx>=0.25.0; extra == 'all'
Requires-Dist: ipython; extra == 'all'
Requires-Dist: itsdangerous>=2.2.0; extra == 'all'
Requires-Dist: jinja2>=3.1.3; extra == 'all'
Requires-Dist: ptpython; extra == 'all'
Requires-Dist: python-magic; extra == 'all'
Requires-Dist: rich-toolkit>=0.14.7; extra == 'all'
Requires-Dist: sayer>=0.7.4; extra == 'all'
Requires-Dist: uvicorn[standard]>=0.29.0; extra == 'all'
Provides-Extra: cli
Requires-Dist: jinja2>=3.1.3; extra == 'cli'
Requires-Dist: rich-toolkit>=0.14.7; extra == 'cli'
Requires-Dist: sayer>=0.7.4; extra == 'cli'
Requires-Dist: uvicorn[standard]>=0.29.0; extra == 'cli'
Provides-Extra: docs
Requires-Dist: griffe-typingdoc<1.0,>=0.2.2; extra == 'docs'
Requires-Dist: mdx-include>=1.4.2; extra == 'docs'
Requires-Dist: mkdocs-macros-plugin>=0.4.0; extra == 'docs'
Requires-Dist: mkdocs-material>=9.4.4; extra == 'docs'
Requires-Dist: mkdocs-meta-descriptions-plugin>=2.3.0; extra == 'docs'
Requires-Dist: mkdocs<2.0.0,>=1.1.2; extra == 'docs'
Requires-Dist: mkdocstrings[python]>=0.23.0; extra == 'docs'
Requires-Dist: pyyaml<7.0.0,>=6.0; extra == 'docs'
Requires-Dist: sayer>=0.7.4; extra == 'docs'
Requires-Dist: typing-extensions>=3.10.0; extra == 'docs'
Provides-Extra: openapi
Requires-Dist: pydantic<3,>=2.11.5; extra == 'openapi'
Provides-Extra: standard
Requires-Dist: itsdangerous>=2.2.0; extra == 'standard'
Requires-Dist: jinja2>=3.1.3; extra == 'standard'
Requires-Dist: rich-toolkit>=0.14.7; extra == 'standard'
Requires-Dist: sayer>=0.7.4; extra == 'standard'
Requires-Dist: uvicorn[standard]>=0.29.0; extra == 'standard'
Provides-Extra: test
Requires-Dist: httpx>=0.25.0; extra == 'test'
Provides-Extra: testing
Requires-Dist: a2wsgi<2.0.0,>=1.10.0; extra == 'testing'
Requires-Dist: anyio[trio]<5.0.0,>=3.6.2; extra == 'testing'
Requires-Dist: asyncz; extra == 'testing'
Requires-Dist: autoflake<3.0.0,>=2.0.2; extra == 'testing'
Requires-Dist: databasez>=0.9.7; extra == 'testing'
Requires-Dist: edgy[postgres]>=0.33.0; extra == 'testing'
Requires-Dist: email-validator>=2.1.0.post1; extra == 'testing'
Requires-Dist: fastapi>=0.121.1; extra == 'testing'
Requires-Dist: flask<4.0.0,>=3.0.2; extra == 'testing'
Requires-Dist: freezegun; extra == 'testing'
Requires-Dist: httpx>=0.25.0; extra == 'testing'
Requires-Dist: ipdb; extra == 'testing'
Requires-Dist: ipython; extra == 'testing'
Requires-Dist: jinja2<4.0.0,>=3.1.3; extra == 'testing'
Requires-Dist: litestar>=2.18.0; extra == 'testing'
Requires-Dist: loguru; extra == 'testing'
Requires-Dist: msgpack; extra == 'testing'
Requires-Dist: msgspec<0.21.0,>=0.20.0; extra == 'testing'
Requires-Dist: mypy==1.19.0; extra == 'testing'
Requires-Dist: opentelemetry-exporter-otlp; extra == 'testing'
Requires-Dist: opentelemetry-sdk; extra == 'testing'
Requires-Dist: orjson; extra == 'testing'
Requires-Dist: ptpython; extra == 'testing'
Requires-Dist: pydantic<3,>=2.6.0; extra == 'testing'
Requires-Dist: pyjwt; extra == 'testing'
Requires-Dist: pytest-asyncio>=0.23.2; extra == 'testing'
Requires-Dist: pytest-cov<5.0.0,>=4.0.0; extra == 'testing'
Requires-Dist: pytest-mock>=3.12.0; extra == 'testing'
Requires-Dist: pytest<9.0.0,>=7.2.2; extra == 'testing'
Requires-Dist: python-magic; extra == 'testing'
Requires-Dist: python-multipart>=0.0.13; extra == 'testing'
Requires-Dist: pyyaml<7.0.0,>=6.0; extra == 'testing'
Requires-Dist: redis; extra == 'testing'
Requires-Dist: structlog; extra == 'testing'
Requires-Dist: typing-extensions>=3.10.0; extra == 'testing'
